cosapp_creator/_version.py
cosapp_creator/cli.py
cosapp_creator/manage.py
cosapp_creator/cosapp_creator/__init__.py
cosapp_creator/cosapp_creator/asgi.py
cosapp_creator/cosapp_creator/settings.py
cosapp_creator/cosapp_creator/urls.py
cosapp_creator/cosapp_creator/views.py
cosapp_creator/cosapp_creator/wsgi.py
cosapp_creator/cosapp_creator/view/__init__.py
cosapp_creator/cosapp_creator_api/__init__.py
cosapp_creator/cosapp_creator_api/admin.py
cosapp_creator/cosapp_creator_api/apps.py
cosapp_creator/cosapp_creator_api/models.py
cosapp_creator/cosapp_creator_api/serializers.py
cosapp_creator/cosapp_creator_api/urls.py
cosapp_creator/cosapp_creator_api/views.py
cosapp_creator/cosapp_creator_api/migrations/0001_initial.py
cosapp_creator/cosapp_creator_api/migrations/0002_auto_20230309_1544.py
cosapp_creator/cosapp_creator_api/migrations/__init__.py
cosapp_creator/cosapp_creator_api/validateConnections/__init__.py
cosapp_creator/cosapp_creator_api/validateConnections/checkLoops.py
cosapp_creator/cosapp_creator_api/validateConnections/createAssembly.py
cosapp_creator/cosapp_creator_api/validateConnections/customAssert.py
cosapp_creator/cosapp_creator_api/validateConnections/detectConnError.py
cosapp_creator/cosapp_creator_api/validateConnections/requestData.py
cosapp_creator/cosapp_creator_api/validateConnections/test_createAssembly.py
cosapp_creator/cosapp_creator_api/validateConnections/test_detectConnError.py
cosapp_creator/cosapp_creator_api/validateConnections/test_requestData.py
cosapp_creator/dist/index.html
cosapp_creator/dist/index.html.j2
cosapp_creator/dist/assets/index.css
cosapp_creator/dist/assets/index.js
cosapp_creator/template/index.html.j2
cosapp_creator-0.1.1.dist-info/METADATA
cosapp_creator-0.1.1.dist-info/WHEEL
cosapp_creator-0.1.1.dist-info/entry_points.txt
cosapp_creator-0.1.1.dist-info/licenses/AUTHORS.md
cosapp_creator-0.1.1.dist-info/licenses/LICENSE
cosapp_creator-0.1.1.dist-info/RECORD
