Metadata-Version: 2.3
Name: cosapp-creator
Version: 0.1.1
Summary: A Django app providing Rest APIs to create CosApp system.
Author: Virginie Zell
License: Copyright (C) 2023-2024 Safran SA - All Rights Reserved
License-File: AUTHORS.md
License-File: LICENSE
Classifier: Environment :: Web Environment
Classifier: Framework :: Django
Classifier: Framework :: Django :: 3.2
Classifier: Intended Audience :: Developers
Classifier: License :: OSI Approved :: Apache Software License
Classifier: Operating System :: OS Independent
Classifier: Programming Language :: Python
Classifier: Programming Language :: Python :: 3
Classifier: Programming Language :: Python :: 3 :: Only
Classifier: Programming Language :: Python :: 3.8
Classifier: Programming Language :: Python :: 3.9
Classifier: Programming Language :: Python :: 3.10
Requires-Dist: cosapp~=0.16
Requires-Dist: django
Requires-Dist: django-cors-headers
Requires-Dist: djangorestframework
